pyroll/neutral_point_estimator/__init__.py
pyroll/neutral_point_estimator/equal_neutral_line_estimator.py
pyroll/neutral_point_estimator/ford_ellis_bland_neutral_line_estimator.py
pyroll/neutral_point_estimator/lichansky_polyakov_ribbed_profile_neutral_point.py
pyroll/neutral_point_estimator/napatov_ribbed_profile_neutral_point.py
pyroll/neutral_point_estimator/osborn_neutral_point_estimator.py
pyroll/neutral_point_estimator/siebel_neutral_point_estimator.py
pyroll/neutral_point_estimator/sims_neutral_point_estimator.py
pyroll/neutral_point_estimator/utils.py
pyroll_neutral_point_estimator-3.0.0.dist-info/METADATA
pyroll_neutral_point_estimator-3.0.0.dist-info/WHEEL
pyroll_neutral_point_estimator-3.0.0.dist-info/licenses/LICENSE
pyroll_neutral_point_estimator-3.0.0.dist-info/RECORD
