Metadata-Version: 2.3
Name: pyroll-neutral-point-estimator
Version: 3.0.0
Summary: Plugin for PyRolL providing a variety of neutral point estimators.
Project-URL: Homepage, https://pyroll-project.github.io
Project-URL: Repository, https://github.com/pyroll-project/pyroll-neutral-point-estimator
Project-URL: Documentation, https://github.com/pyroll-project/pyroll-neutral-point-estimator/blob/main/docs/docs.pdf
Author-email: Christoph Renzing <christoph.renzing@imf.tu-freiberg.de>
License-Expression: BSD-3-Clause
License-File: LICENSE
Classifier: Intended Audience :: Manufacturing
Classifier: Intended Audience :: Science/Research
Classifier: Operating System :: OS Independent
Classifier: Topic :: Scientific/Engineering
Requires-Python: <4.0,>=3.9
Requires-Dist: pyroll-core~=3.0
Requires-Dist: pyroll-interface-friction~=3.0
